ansitom/__init__.py
ansitom-0.0.2.dist-info/DESCRIPTION.rst
ansitom-0.0.2.dist-info/LICENSE.txt
ansitom-0.0.2.dist-info/METADATA
ansitom-0.0.2.dist-info/RECORD
ansitom-0.0.2.dist-info/WHEEL
ansitom-0.0.2.dist-info/entry_points.txt
ansitom-0.0.2.dist-info/metadata.json
ansitom-0.0.2.dist-info/top_level.txt
