Metadata-Version: 2.0
Name: ansitom
Version: 0.0.2
Summary: Ansible playbook generator
Home-page: https://github.com/samvarankashyap/ansitom
Author: samvaran kashyap rallabandi
Author-email: samvaran.kashyap@gmail.com
License: UNKNOWN
Platform: UNKNOWN
Requires-Dist: ansible (==2.2.1)
Requires-Dist: click (==6.7)
